tml/.gitignore
tml/__init__.py
tml/apps.py
tml/io.py
tml/parser.py
tml/uml.py
tml/utils.py
tml/widgets.py
tml/static/tml/css/help.css
tml/templates/tml/forms/widgets/textarea.html
tml/templatetags/__init__.py
tml/templatetags/tml.py
tml/tests/__init__.py
tml/tests/test_parser.py
tml/tests/test_parser_closures.py
tml/tests/test_parser_lists.py
tml/tests/test_parser_subclass.py
tml/tests/test_stack.py
tml/tests/test_uml.py
django_ttml-1.0.3.dist-info/LICENSE
django_ttml-1.0.3.dist-info/WHEEL
django_ttml-1.0.3.dist-info/METADATA
django_ttml-1.0.3.dist-info/RECORD
