Metadata-Version: 2.1
Name: django-ttml
Version: 1.0.3
Summary: A reliable markup language with the essentials for HTML typography. Fast to type and memorable. Includes optional UML, for unicode shortcuts.
Home-page: https://github.com/rcrowther/django-tml
Author: Robert Crowther
Author-email: rw.crowther@gmail.com
Classifier: Operating System :: OS Independent
Classifier: License :: OSI Approved :: BSD License
Classifier: Programming Language :: Python :: 3
Classifier: Framework :: Django
